wagtail/__init__.py
wagtail/bin/__init__.py
wagtail/bin/wagtail.py
wagtail/contrib/__init__.py
wagtail/contrib/settings/.gitignore
wagtail/contrib/settings/__init__.py
wagtail/contrib/settings/apps.py
wagtail/contrib/settings/context_processors.py
wagtail/contrib/settings/forms.py
wagtail/contrib/settings/models.py
wagtail/contrib/settings/permissions.py
wagtail/contrib/settings/registry.py
wagtail/contrib/settings/urls.py
wagtail/contrib/settings/views.py
wagtail/contrib/settings/wagtail_hooks.py
wagtail/contrib/settings/static/wagtailsettings/js/site-switcher.js
wagtail/contrib/settings/static_src/wagtailsettings/js/site-switcher.js
wagtail/contrib/settings/templates/wagtailsettings/edit.html
wagtail/contrib/settings/templates/wagtailsettings/index.html
wagtail/contrib/settings/templatetags/__init__.py
wagtail/contrib/settings/templatetags/wagtailsettings_tags.py
wagtail/contrib/settings/tests/__init__.py
wagtail/contrib/settings/tests/test_admin.py
wagtail/contrib/settings/tests/test_register.py
wagtail/contrib/settings/tests/test_templates.py
wagtail/contrib/wagtailapi/__init__.py
wagtail/contrib/wagtailapi/apps.py
wagtail/contrib/wagtailapi/endpoints.py
wagtail/contrib/wagtailapi/filters.py
wagtail/contrib/wagtailapi/pagination.py
wagtail/contrib/wagtailapi/router.py
wagtail/contrib/wagtailapi/serializers.py
wagtail/contrib/wagtailapi/signal_handlers.py
wagtail/contrib/wagtailapi/urls.py
wagtail/contrib/wagtailapi/utils.py
wagtail/contrib/wagtailapi/tests/__init__.py
wagtail/contrib/wagtailapi/tests/test_documents.py
wagtail/contrib/wagtailapi/tests/test_images.py
wagtail/contrib/wagtailapi/tests/test_pages.py
wagtail/contrib/wagtailfrontendcache/__init__.py
wagtail/contrib/wagtailfrontendcache/apps.py
wagtail/contrib/wagtailfrontendcache/backends.py
wagtail/contrib/wagtailfrontendcache/models.py
wagtail/contrib/wagtailfrontendcache/signal_handlers.py
wagtail/contrib/wagtailfrontendcache/tests.py
wagtail-1.3.1.dist-info/DESCRIPTION.rst
wagtail-1.3.1.dist-info/entry_points.txt
wagtail-1.3.1.dist-info/METADATA
wagtail-1.3.1.dist-info/metadata.json
wagtail-1.3.1.dist-info/RECORD
wagtail-1.3.1.dist-info/top_level.txt
wagtail-1.3.1.dist-info/WHEEL
