Metadata-Version: 2.0
Name: wagtail
Version: 1.3.1
Summary: A Django content management system focused on flexibility and user experience
Home-page: http://wagtail.io/
Author: Matthew Westcott
Author-email: matthew.westcott@torchbox.com
License: BSD
Platform: UNKNOWN
Classifier: Development Status :: 5 - Production/Stable
Classifier: Environment :: Web Environment
Classifier: Intended Audience :: Developers
Classifier: License :: OSI Approved :: BSD License
Classifier: Operating System :: OS Independent
Classifier: Programming Language :: Python
Classifier: Programming Language :: Python :: 2
Classifier: Programming Language :: Python :: 2.7
Classifier: Programming Language :: Python :: 3
Classifier: Programming Language :: Python :: 3.3
Classifier: Programming Language :: Python :: 3.4
Classifier: Programming Language :: Python :: 3.5
Classifier: Framework :: Django
Classifier: Framework :: Django :: 1.7
Classifier: Framework :: Django :: 1.8
Classifier: Framework :: Django :: 1.9
Classifier: Topic :: Internet :: WWW/HTTP :: Site Management
Requires-Dist: Django (>=1.7.1,<1.10)
Requires-Dist: django-compressor (>=1.4)
Requires-Dist: django-modelcluster (>=1.1)
Requires-Dist: django-taggit (>=0.17.5)
Requires-Dist: django-treebeard (==3.0)
Requires-Dist: djangorestframework (>=3.1.3)
Requires-Dist: Pillow (>=2.6.1)
Requires-Dist: beautifulsoup4 (>=4.3.2)
Requires-Dist: html5lib (>=0.999,<1)
Requires-Dist: Unidecode (>=0.04.14)
Requires-Dist: Willow (>=0.2.2,<0.3)
